<annotation>
	<folder>dataset3</folder>
	<filename>image10166.jpg</filename>
	<path>/root/TensorFlow/dataset3/image10166.jpg</path>
	<source>
		<database>Unknown</database>
	</source>
	<size>
		<width>301</width>
		<height>167</height>
		<depth>3</depth>
	</size>
	<segmented>0</segmented>
	<object>
		<name>nohelmet</name>
		<pose>Unspecified</pose>
		<truncated>1</truncated>
		<difficult>0</difficult>
		<bndbox>
			<xmin>107</xmin>
			<ymin>2</ymin>
			<xmax>195</xmax>
			<ymax>167</ymax>
		</bndbox>
	</object>
</annotation>
