<annotation>
	<folder>nohelmet</folder>
	<filename>image1079.jpg</filename>
	<path>/root/TensorFlow/Dataset/nohelmet/image1079.jpg</path>
	<source>
		<database>Unknown</database>
	</source>
	<size>
		<width>2340</width>
		<height>4160</height>
		<depth>3</depth>
	</size>
	<segmented>0</segmented>
	<object>
		<name>nohelmet</name>
		<pose>Unspecified</pose>
		<truncated>0</truncated>
		<difficult>0</difficult>
		<bndbox>
			<xmin>970</xmin>
			<ymin>373</ymin>
			<xmax>1670</xmax>
			<ymax>1879</ymax>
		</bndbox>
	</object>
</annotation>
