<annotation>
	<folder>nohelmet</folder>
	<filename>image213.jpg</filename>
	<path>/root/TensorFlow/Dataset/nohelmet/image213.jpg</path>
	<source>
		<database>Unknown</database>
	</source>
	<size>
		<width>2340</width>
		<height>4160</height>
		<depth>3</depth>
	</size>
	<segmented>0</segmented>
	<object>
		<name>nohelmet</name>
		<pose>Unspecified</pose>
		<truncated>0</truncated>
		<difficult>0</difficult>
		<bndbox>
			<xmin>763</xmin>
			<ymin>1113</ymin>
			<xmax>1717</xmax>
			<ymax>2639</ymax>
		</bndbox>
	</object>
</annotation>
